pyqt6spinner/__init__.py
pyqt6spinner/configurator.py
pyqt6spinner/spinner.py
pyqt6spinner-2.0.0.dist-info/entry_points.txt
pyqt6spinner-2.0.0.dist-info/licenses/LICENSE
pyqt6spinner-2.0.0.dist-info/METADATA
pyqt6spinner-2.0.0.dist-info/WHEEL
pyqt6spinner-2.0.0.dist-info/RECORD
