Metadata-Version: 2.4
Name: pyqt6spinner
Version: 2.0.0
Summary: Waiting spinner for PyQt6
License-Expression: MIT
License-File: LICENSE
Author: Denis
Author-email: fbjorn@users.noreply.github.com
Requires-Python: >=3.11,<4.0
Classifier: Environment :: X11 Applications :: Qt
Classifier: Environment :: X11 Applications
Classifier: Intended Audience :: Developers
Classifier: Intended Audience :: Information Technology
Classifier: License :: OSI Approved :: MIT License
Classifier: Operating System :: OS Independent
Classifier: Programming Language :: Python :: 3
Classifier: Topic :: Software Development :: Libraries :: Python Modules
Classifier: Topic :: Software Development :: Libraries
Classifier: Topic :: Software Development
Requires-Dist: pyqt6 (>=6.10.1,<7.0.0)
Project-URL: Repository, https://github.com/Bahadorrj/QtWaitingSpinner.git
